cliq/__init__.py
cliq/core/__init__.py
cliq/core/config.py
cliq/core/init.py
cliq/main/__init__.py
cliq/main/cli.py
cliq/main/commander.py
cliq/main/command/__init__.py
cliq/main/command/config.py
cliq/main/command/create.py
cliq/main/command/help.py
cliq/main/command/init.py
cliq/sample_commands/please.py
cliq/sample_commands/say.py
cliq/templates/command/complex.py
cliq/templates/command/simple.py
cliq/templates/library/__init__.py
cliq/templates/module/__init__.py
cliq/templates/module/main/__init__.py
cliq/templates/module/main/command/config.py
cliq/templates/module/main/command/help.py
cliq/templates/module/main/command/init.py
cliq/templates/project/setup.cfg
cliq/templates/project/setup.py
cliq-0.9.3.dist-info/LICENSE
cliq-0.9.3.dist-info/METADATA
cliq-0.9.3.dist-info/WHEEL
cliq-0.9.3.dist-info/entry_points.txt
cliq-0.9.3.dist-info/top_level.txt
cliq-0.9.3.dist-info/RECORD
