Metadata-Version: 2.1
Name: cliq
Version: 0.9.3
Summary: a lightweight framework for creating command line interfaces quickly
Home-page: https://github.com/youhyunjo/cliq
Author: youhyunjo
Author-email: you@cpan.org
License: GPLv3+
Keywords: cli framework
Platform: UNKNOWN
Classifier: Programming Language :: Python :: 3
Classifier: License :: OSI Approved :: GNU General Public License v3 or later (GPLv3+)
Classifier: Operating System :: OS Independent
Requires-Python: >=3.5
License-File: LICENSE
